{
    "version": "0.10.5",
    "architecture": {
        "64bit": {
            "url": "https://github.com/aripalo/vegas-credentials/releases/download/v0.10.5/vegas-credentials_0.10.5_windows_amd64.tar.gz",
            "bin": [
                "vegas-credentials.exe"
            ],
            "hash": "e4b9ce8d9f33b8e10ddd7403c2129282539e2c56697555e5c4f27ebb140e3f99"
        }
    },
    "homepage": "https://github.com/aripalo/vegas-credentials",
    "license": "Apache-2.0",
    "description": "A helper utility that plugs into standard credential_process to assume AWS IAM Role with – Yubikey Touch and Authenticator App – TOTP MFA to provide session credentials – with automatic refreshing."
}